{
 "seed": "http://www.victoriagc.co.kr/",
 "pages": {
  "p0.html": "http://www.victoriagc.co.kr/",
  "p1.html": "https://www.victoriagc.co.kr/02guide/01guide.asp",
  "p2.html": "https://www.victoriagc.co.kr/02guide/02guide.asp",
  "p3.html": "https://www.victoriagc.co.kr/02guide/03charge.asp",
  "p4.html": "https://www.victoriagc.co.kr/02guide/04rule.asp",
  "p5.html": "https://www.victoriagc.co.kr/03join/joinGuide.asp",
  "p6.html": "https://www.victoriagc.co.kr/04course/courseIntro.asp",
  "p7.html": "https://www.victoriagc.co.kr/04course/p1.asp",
  "p8.html": "https://www.victoriagc.co.kr/02guide/05clause.asp",
  "p9.html": "https://www.victoriagc.co.kr/04course/p2.asp",
  "p10.html": "https://www.victoriagc.co.kr/04course/p3.asp",
  "p11.html": "https://www.victoriagc.co.kr/04course/p4.asp"
 },
 "images": {},
 "errors": []
}