{
 "name": "사이언스 대덕 CC",
 "seed": "http://www.ddgolf.co.kr/",
 "pages": {
  "p0.html": "http://www.ddgolf.co.kr/",
  "p1.html": "http://www.ddgolf.co.kr/02course/course01.asp",
  "p2.html": "http://www.ddgolf.co.kr/02course/course02.asp",
  "p3.html": "http://www.ddgolf.co.kr/02course/course01_2.asp",
  "p4.html": "http://www.ddgolf.co.kr/02course/course01_2_2.asp",
  "p5.html": "http://www.ddgolf.co.kr/02course/course01_2_3.asp",
  "p6.html": "http://www.ddgolf.co.kr/02course/course01_2_4.asp",
  "p7.html": "http://www.ddgolf.co.kr/02course/course01_2_5.asp",
  "p8.html": "http://www.ddgolf.co.kr/02course/course01_2_6.asp",
  "p9.html": "http://www.ddgolf.co.kr/02course/course01_2_7.asp",
  "p10.html": "http://www.ddgolf.co.kr/02course/course01_2_8.asp",
  "p11.html": "http://www.ddgolf.co.kr/02course/course01_2_9.asp"
 },
 "images": {
  "2011.jpg": "http://www.ddgolf.co.kr/image/2011.jpg",
  "2019.jpg": "http://www.ddgolf.co.kr/image/2019.jpg",
  "2015.jpg": "http://www.ddgolf.co.kr/image/2015.jpg",
  "2010.jpg": "http://www.ddgolf.co.kr/image/2010.jpg",
  "2018.jpg": "http://www.ddgolf.co.kr/image/2018.jpg",
  "2017.jpg": "http://www.ddgolf.co.kr/image/2017.jpg",
  "2012.jpg": "http://www.ddgolf.co.kr/image/2012.jpg",
  "2014.jpg": "http://www.ddgolf.co.kr/image/2014.jpg",
  "2013.jpg": "http://www.ddgolf.co.kr/image/2013.jpg",
  "2016.jpg": "http://www.ddgolf.co.kr/image/2016.jpg"
 },
 "errors": [
  "page http://www.ddgolf.co.kr/02course/delete_ok.asp?intIdx=: HTTP Error 500: Internal Server Error"
 ]
}