{"ciCode": 100000603, "ccName": "여주 캐슬 GGC", "detail": {"ciCode": 100000603, "ccName": "여주 캐슬 GGC", "createdAt": "Y", "country": 7, "district": 0, "address": "경기도 여주시 지형을 기반으로 골프존에서 설계한 코스", "tel": "1577-4333", "fax": "-", "homepageUrl": "http://www.golfzon.com ", "description": "", "difficultyGreen": 8, "difficultyCc": 9, "ciStatus": 1, "ciOption": 14, "areaName": "가상CC", "logoImage": "http://uf.gzcdn.net/course/info/202112/1616/28/0a824bdf04da4cb9a915b48fd9d3bdd6.jpg", "holeCount": 18, "parCount": 72, "totalWidth": 6233, "boardCount": 19, "ci3d": "Y", "isOnlyHd": null, "isVisionPlus": "Y", "isNgs": "Y", "isOnlyNgs": null, "isTvnx": "Y", "isNxp": "Y", "ciVersion": 2, "tourCc": 0, "ciNight": 0, "membership": "N", "realityYn": "N", "difficultyYn": "N"}, "holeInfo": {"holeInfoList": [[{"backTee": 381, "basicPar": 4, "ccMasterSeq": 1096, "champTee": 381, "ciCode": 100000603, "ciNum": 1, "ciVersion": 2, "courseTypeOrder": 1, "description": "", "frontTee": 363, "heightBackTee": -1.58, "heightChampTee": -1.57, "heightFrontTee": -1.19, "heightLadySeniorTee": 0.0, "heightLadyTee": 1.4, "heightSeniorTee": 1.4, "holeNo": 1, "ladySeniorTee": 0, "ladyTee": 323, "mapUrl": "/yardage/entire/yardage_entire_1096_01_01.jpg", "oCcMasterSeq": null, "oCiNum": null, "screenshot": "", "seniorTee": 323, "videoMapUrl": "hole3D_1096_01_01"}, {"backTee": 372, "basicPar": 4, "ccMasterSeq": 1096, "champTee": 372, "ciCode": 100000603, "ciNum": 1, "ciVersion": 2, "courseTypeOrder": 1, "description": "", "frontTee": 333, "heightBackTee": 0.44, "heightChampTee": 0.42, "heightFrontTee": 0.77, "heightLadySeniorTee": 0.0, "heightLadyTee": 0.69, "heightSeniorTee": 0.69, "holeNo": 2, "ladySeniorTee": 0, "ladyTee": 306, "mapUrl": "/yardage/entire/yardage_entire_1096_01_02.jpg", "oCcMasterSeq": null, "oCiNum": null, "screenshot": "", "seniorTee": 306, "videoMapUrl": "hole3D_1096_01_02"}, {"backTee": 329, "basicPar": 4, "ccMasterSeq": 1096, "champTee": 328, "ciCode": 100000603, "ciNum": 1, "ciVersion": 2, "courseTypeOrder": 1, "description": "", "frontTee": 298, "heightBackTee": 8.72, "heightChampTee": 8.74, "heightFrontTee": 9.75, "heightLadySeniorTee": 0.0, "heightLadyTee": 9.97, "heightSeniorTee": 10.01, "holeNo": 3, "ladySeniorTee": 0, "ladyTee": 264, "mapUrl": "/yardage/entire/yardage_entire_1096_01_03.jpg", "oCcMasterSeq": null, "oCiNum": null, "screenshot": "", "seniorTee": 264, "videoMapUrl": "hole3D_1096_01_03"}, {"backTee": 487, "basicPar": 5, "ccMasterSeq": 1096, "champTee": 487, "ciCode": 100000603, "ciNum": 1, "ciVersion": 2, "courseTypeOrder": 1, "description": "", "frontTee": 454, "heightBackTee": -54.75, "heightChampTee": -54.73, "heightFrontTee": -52.21, "heightLadySeniorTee": 0.0, "heightLadyTee": -44.45, "heightSeniorTee": -44.45, "holeNo": 4, "ladySeniorTee": 0, "ladyTee": 373, "mapUrl": "/yardage/entire/yardage_entire_1096_01_04.jpg", "oCcMasterSeq": null, "oCiNum": null, "screenshot": "", "seniorTee": 373, "videoMapUrl": "hole3D_1096_01_04"}, {"backTee": 162, "basicPar": 3, "ccMasterSeq": 1096, "champTee": 161, "ciCode": 100000603, "ciNum": 1, "ciVersion": 2, "courseTypeOrder": 1, "description": "", "frontTee": 145, "heightBackTee": 1.66, "heightChampTee": 1.66, "heightFrontTee": 2.31, "heightLadySeniorTee": 0.0, "heightLadyTee": 1.77, "heightSeniorTee": 1.77, "holeNo": 5, "ladySeniorTee": 0, "ladyTee": 109, "mapUrl": "/yardage/entire/yardage_entire_1096_01_05.jpg", "oCcMasterSeq": null, "oCiNum": null, "screenshot": "", "seniorTee": 109, "videoMapUrl": "hole3D_1096_01_05"}, {"backTee": 362, "basicPar": 4, "ccMasterSeq": 1096, "champTee": 362, "ciCode": 100000603, "ciNum": 1, "ciVersion": 2, "courseTypeOrder": 1, "description": "", "frontTee": 321, "heightBackTee": -41.04, "heightChampTee": -41.0, "heightFrontTee": -33.67, "heightLadySeniorTee": 0.0, "heightLadyTee": -28.1, "heightSeniorTee": -28.1, "holeNo": 6, "ladySeniorTee": 0, "ladyTee": 275, "mapUrl": "/yardage/entire/yardage_entire_1096_01_06.jpg", "oCcMasterSeq": null, "oCiNum": null, "screenshot": "", "seniorTee": 275, "videoMapUrl": "hole3D_1096_01_06"}, {"backTee": 174, "basicPar": 3, "ccMasterSeq": 1096, "champTee": 174, "ciCode": 100000603, "ciNum": 1, "ciVersion": 2, "courseTypeOrder": 1, "description": "", "frontTee": 167, "heightBackTee": -2.41, "heightChampTee": -2.43, "heightFrontTee": -2.44, "heightLadySeniorTee": 0.0, "heightLadyTee": -0.18, "heightSeniorTee": -0.18, "holeNo": 7, "ladySeniorTee": 0, "ladyTee": 139, "mapUrl": "/yardage/entire/yardage_entire_1096_01_07.jpg", "oCcMasterSeq": null, "oCiNum": null, "screenshot": "", "seniorTee": 139, "videoMapUrl": "hole3D_1096_01_07"}, {"backTee": 375, "basicPar": 4, "ccMasterSeq": 1096, "champTee": 375, "ciCode": 100000603, "ciNum": 1, "ciVersion": 2, "courseTypeOrder": 1, "description": "", "frontTee": 363, "heightBackTee": -2.7, "heightChampTee": -2.71, "heightFrontTee": -2.34, "heightLadySeniorTee": 0.0, "heightLadyTee": -1.49, "heightSeniorTee": -1.49, "holeNo": 8, "ladySeniorTee": 0, "ladyTee": 342, "mapUrl": "/yardage/entire/yardage_entire_1096_01_08.jpg", "oCcMasterSeq": null, "oCiNum": null, "screenshot": "", "seniorTee": 342, "videoMapUrl": "hole3D_1096_01_08"}, {"backTee": 489, "basicPar": 5, "ccMasterSeq": 1096, "champTee": 488, "ciCode": 100000603, "ciNum": 1, "ciVersion": 2, "courseTypeOrder": 1, "description": "", "frontTee": 451, "heightBackTee": -0.48, "heightChampTee": -0.47, "heightFrontTee": 1.03, "heightLadySeniorTee": 0.0, "heightLadyTee": 2.27, "heightSeniorTee": 2.27, "holeNo": 9, "ladySeniorTee": 0, "ladyTee": 426, "mapUrl": "/yardage/entire/yardage_entire_1096_01_09.jpg", "oCcMasterSeq": null, "oCiNum": null, "screenshot": "", "seniorTee": 426, "videoMapUrl": "hole3D_1096_01_09"}], [{"backTee": 380, "basicPar": 4, "ccMasterSeq": 1096, "champTee": 380, "ciCode": 100000603, "ciNum": 2, "ciVersion": 2, "courseTypeOrder": 2, "description": "", "frontTee": 345, "heightBackTee": -3.12, "heightChampTee": -3.1, "heightFrontTee": -2.64, "heightLadySeniorTee": 0.0, "heightLadyTee": -2.05, "heightSeniorTee": -2.02, "holeNo": 1, "ladySeniorTee": 0, "ladyTee": 328, "mapUrl": "/yardage/entire/yardage_entire_1096_02_01.jpg", "oCcMasterSeq": null, "oCiNum": null, "screenshot": "", "seniorTee": 328, "videoMapUrl": "hole3D_1096_02_01"}, {"backTee": 356, "basicPar": 4, "ccMasterSeq": 1096, "champTee": 356, "ciCode": 100000603, "ciNum": 2, "ciVersion": 2, "courseTypeOrder": 2, "description": "", "frontTee": 339, "heightBackTee": -11.52, "heightChampTee": -11.56, "heightFrontTee": -9.37, "heightLadySeniorTee": 0.0, "heightLadyTee": -7.41, "heightSeniorTee": -7.42, "holeNo": 2, "ladySeniorTee": 0, "ladyTee": 318, "mapUrl": "/yardage/entire/yardage_entire_1096_02_02.jpg", "oCcMasterSeq": null, "oCiNum": null, "screenshot": "", "seniorTee": 318, "videoMapUrl": "hole3D_1096_02_02"}, {"backTee": 362, "basicPar": 4, "ccMasterSeq": 1096, "champTee": 362, "ciCode": 100000603, "ciNum": 2, "ciVersion": 2, "courseTypeOrder": 2, "description": "", "frontTee": 345, "heightBackTee": -19.12, "heightChampTee": -19.13, "heightFrontTee": -16.97, "heightLadySeniorTee": 0.0, "heightLadyTee": -15.98, "heightSeniorTee": -15.98, "holeNo": 3, "ladySeniorTee": 0, "ladyTee": 330, "mapUrl": "/yardage/entire/yardage_entire_1096_02_03.jpg", "oCcMasterSeq": null, "oCiNum": null, "screenshot": "", "seniorTee": 330, "videoMapUrl": "hole3D_1096_02_03"}, {"backTee": 186, "basicPar": 3, "ccMasterSeq": 1096, "champTee": 186, "ciCode": 100000603, "ciNum": 2, "ciVersion": 2, "courseTypeOrder": 2, "description": "", "frontTee": 162, "heightBackTee": -16.56, "heightChampTee": -16.52, "heightFrontTee": -13.3, "heightLadySeniorTee": 0.0, "heightLadyTee": -11.48, "heightSeniorTee": -11.48, "holeNo": 4, "ladySeniorTee": 0, "ladyTee": 151, "mapUrl": "/yardage/entire/yardage_entire_1096_02_04.jpg", "oCcMasterSeq": null, "oCiNum": null, "screenshot": "", "seniorTee": 152, "videoMapUrl": "hole3D_1096_02_04"}, {"backTee": 504, "basicPar": 5, "ccMasterSeq": 1096, "champTee": 504, "ciCode": 100000603, "ciNum": 2, "ciVersion": 2, "courseTypeOrder": 2, "description": "", "frontTee": 493, "heightBackTee": -12.56, "heightChampTee": -12.57, "heightFrontTee": -12.56, "heightLadySeniorTee": 0.0, "heightLadyTee": -8.87, "heightSeniorTee": -8.87, "holeNo": 5, "ladySeniorTee": 0, "ladyTee": 427, "mapUrl": "/yardage/entire/yardage_entire_1096_02_05.jpg", "oCcMasterSeq": null, "oCiNum": null, "screenshot": "", "seniorTee": 427, "videoMapUrl": "hole3D_1096_02_05"}, {"backTee": 545, "basicPar": 5, "ccMasterSeq": 1096, "champTee": 545, "ciCode": 100000603, "ciNum": 2, "ciVersion": 2, "courseTypeOrder": 2, "description": "", "frontTee": 509, "heightBackTee": 1.9, "heightChampTee": 1.83, "heightFrontTee": 3.96, "heightLadySeniorTee": 0.0, "heightLadyTee": 8.06, "heightSeniorTee": 8.06, "holeNo": 6, "ladySeniorTee": 0, "ladyTee": 451, "mapUrl": "/yardage/entire/yardage_entire_1096_02_06.jpg", "oCcMasterSeq": null, "oCiNum": null, "screenshot": "", "seniorTee": 451, "videoMapUrl": "hole3D_1096_02_06"}, {"backTee": 179, "basicPar": 3, "ccMasterSeq": 1096, "champTee": 178, "ciCode": 100000603, "ciNum": 2, "ciVersion": 2, "courseTypeOrder": 2, "description": "", "frontTee": 163, "heightBackTee": -4.93, "heightChampTee": -4.93, "heightFrontTee": -4.24, "heightLadySeniorTee": 0.0, "heightLadyTee": -2.7, "heightSeniorTee": -2.7, "holeNo": 7, "ladySeniorTee": 0, "ladyTee": 147, "mapUrl": "/yardage/entire/yardage_entire_1096_02_07.jpg", "oCcMasterSeq": null, "oCiNum": null, "screenshot": "", "seniorTee": 147, "videoMapUrl": "hole3D_1096_02_07"}, {"backTee": 303, "basicPar": 4, "ccMasterSeq": 1096, "champTee": 302, "ciCode": 100000603, "ciNum": 2, "ciVersion": 2, "courseTypeOrder": 2, "description": "", "frontTee": 276, "heightBackTee": 12.2, "heightChampTee": 12.4, "heightFrontTee": 10.92, "heightLadySeniorTee": 0.0, "heightLadyTee": 5.59, "heightSeniorTee": 5.59, "holeNo": 8, "ladySeniorTee": 0, "ladyTee": 249, "mapUrl": "/yardage/entire/yardage_entire_1096_02_08.jpg", "oCcMasterSeq": null, "oCiNum": null, "screenshot": "", "seniorTee": 249, "videoMapUrl": "hole3D_1096_02_08"}, {"backTee": 287, "basicPar": 4, "ccMasterSeq": 1096, "champTee": 287, "ciCode": 100000603, "ciNum": 2, "ciVersion": 2, "courseTypeOrder": 2, "description": "", "frontTee": 270, "heightBackTee": 22.52, "heightChampTee": 22.5, "heightFrontTee": 23.38, "heightLadySeniorTee": 0.0, "heightLadyTee": 18.56, "heightSeniorTee": 18.62, "holeNo": 9, "ladySeniorTee": 0, "ladyTee": 225, "mapUrl": "/yardage/entire/yardage_entire_1096_02_09.jpg", "oCcMasterSeq": null, "oCiNum": null, "screenshot": "", "seniorTee": 225, "videoMapUrl": "hole3D_1096_02_09"}]], "courseTypes": [{"ciCode": 100000603, "ciNum": 1, "courseName": "OUT"}, {"ciCode": 100000603, "ciNum": 2, "courseName": "IN"}]}}