{"ciCode": 100000022, "ccName": "웨스트오션 CC", "detail": {"ciCode": 100000022, "ccName": "웨스트오션 CC", "createdAt": "Y", "country": 1, "district": 4, "address": "전라남도 영광군 백수읍 구수리 산40-18", "tel": "061-350-2000", "fax": "061-350-2022", "homepageUrl": "http://www.ygcc.co.kr/", "description": "<p><span style=\"font-size: 10pt;\"><span style=\"COLOR: #6b8e23\"><span style=\"font-size: 10pt; color: rgb(102, 102, 102);\"><span style=\"COLOR: #6b8e23\"><span style=\"font-size: 10pt;\"><span style=\"font-size: 10pt;\"><span style=\"font-size: 10pt;\"><span style=\"font-size: 10pt;\"><strong>&ldquo;웨스트오션 CC만의 색다른 세계로의 초대&rdquo;</strong></span></span></span></span></span></span></span><br />\n특별한 만남, 특별한 기대가 가득한 영광컨트리클럽은 기암괴석과 서해바다, 계곡과 호수가 한데 어우러진 천혜의 장관을 이루고 차별화된 놀라움이 가득한 골프코스로 인간과 자연의 완벽한 조화를 추구합니다.</span></p>\n\n<p>&nbsp;</p>", "difficultyGreen": 6, "difficultyCc": 7, "ciStatus": 1, "ciOption": 15, "areaName": "전라도", "logoImage": "http://uf.gzcdn.net/course/info/202311/2819/49/af58372ef53a4264a950f4ffd69363f2.jpg", "holeCount": 18, "parCount": 72, "totalWidth": 6220, "boardCount": 125, "ci3d": "Y", "isOnlyHd": null, "isVisionPlus": "Y", "isNgs": "Y", "isOnlyNgs": null, "isTvnx": "Y", "isNxp": "Y", "ciVersion": 2, "tourCc": 0, "ciNight": 0, "membership": "N", "realityYn": "N", "difficultyYn": "N"}, "holeInfo": {"holeInfoList": [[{"backTee": 375, "basicPar": 4, "ccMasterSeq": 157, "champTee": 375, "ciCode": 100000022, "ciNum": 1, "ciVersion": 2, "courseTypeOrder": 1, "description": "파4홀로 페어웨이 좌측에 위치한 벙커 우측 끝선을 IP로 설정하는 것이 좋습니다. 세컨샷은 그린 좌측에 위치한 벙커를 조심하여 그린 중앙으로 공략하는 것이 좋습니다. 그린도 비교적 크기 때문에 투온만 시키신다면 무난히 파를 기록할 수 있는 홀 입니다", "frontTee": 350, "heightBackTee": -1.6601, "heightChampTee": -1.6601, "heightFrontTee": -0.589, "heightLadySeniorTee": 0.0, "heightLadyTee": 1.6113, "heightSeniorTee": 0.6076, "holeNo": 1, "ladySeniorTee": 0, "ladyTee": 265, "mapUrl": "/yardage/entire/yardage_entire_157_01_01.jpg", "oCcMasterSeq": null, "oCiNum": null, "screenshot": "screenshot_100000022_1_01.jpg", "seniorTee": 315, "videoMapUrl": "hole3D_157_01_01"}, {"backTee": 375, "basicPar": 4, "ccMasterSeq": 157, "champTee": 375, "ciCode": 100000022, "ciNum": 1, "ciVersion": 2, "courseTypeOrder": 1, "description": "파4홀로 페어웨이 티샷IP지점 좌측에 벙커가 있으므로 페어웨이 공략에 신중해야 합니다. 그린공략에는 그린우측에 여유가 없으므로 약간만 슬라이스가 나와도 위험하므로 신중하게 세컨샷을 해야 합니다", "frontTee": 360, "heightBackTee": -21.4506, "heightChampTee": -21.4506, "heightFrontTee": -19.1634, "heightLadySeniorTee": 0.0, "heightLadyTee": -11.353, "heightSeniorTee": -17.3784, "holeNo": 2, "ladySeniorTee": 0, "ladyTee": 295, "mapUrl": "/yardage/entire/yardage_entire_157_01_02.jpg", "oCcMasterSeq": null, "oCiNum": null, "screenshot": "screenshot_100000022_1_02(2).jpg", "seniorTee": 340, "videoMapUrl": "hole3D_157_01_02"}, {"backTee": 465, "basicPar": 5, "ccMasterSeq": 157, "champTee": 465, "ciCode": 100000022, "ciNum": 1, "ciVersion": 2, "courseTypeOrder": 1, "description": "파5홀로 페어웨이 좌측에 보이는 벙커끝선을 IP로 설정하는 것이 좋습니다. 세컨샷은 그린 앞의 벙커 우측 끝선을 겨누는 것이 좋으며 그린 공략시에는 세개의 벙커를 유념하여야 합니다. 그리고 그린이 포대 그린이므로 그린 중앙을 공략하는 것이 좋습니다", "frontTee": 445, "heightBackTee": -0.2173, "heightChampTee": -0.2173, "heightFrontTee": 2.3687, "heightLadySeniorTee": 0.0, "heightLadyTee": 11.7378, "heightSeniorTee": 6.0405, "holeNo": 3, "ladySeniorTee": 0, "ladyTee": 380, "mapUrl": "/yardage/entire/yardage_entire_157_01_03.jpg", "oCcMasterSeq": null, "oCiNum": null, "screenshot": "screenshot_100000022_1_03.jpg", "seniorTee": 415, "videoMapUrl": "hole3D_157_01_03"}, {"backTee": 160, "basicPar": 3, "ccMasterSeq": 157, "champTee": 160, "ciCode": 100000022, "ciNum": 1, "ciVersion": 2, "courseTypeOrder": 1, "description": "파3홀로 그린이 커서 그린 공략이 무난한 홀 입니다. 그린 뒤로 벙커가 있으므로 거리가 오버되지 않도록 하는 것이 중요한 홀 입니다", "frontTee": 145, "heightBackTee": -0.1452, "heightChampTee": -0.1452, "heightFrontTee": -0.2074, "heightLadySeniorTee": 0.0, "heightLadyTee": -0.0089, "heightSeniorTee": -0.4055, "holeNo": 4, "ladySeniorTee": 0, "ladyTee": 110, "mapUrl": "/yardage/entire/yardage_entire_157_01_04.jpg", "oCcMasterSeq": null, "oCiNum": null, "screenshot": "screenshot_100000022_1_04.jpg", "seniorTee": 131, "videoMapUrl": "hole3D_157_01_04"}, {"backTee": 390, "basicPar": 4, "ccMasterSeq": 157, "champTee": 390, "ciCode": 100000022, "ciNum": 1, "ciVersion": 2, "courseTypeOrder": 1, "description": "내리막 파4홀로 장타자들은 워터해저드에 빠질 수 있으므로 우드나 롱 아이언으로 티샷을 하는 것이 좋습니다. 페어웨이를 잘 지킨다면 평탄한 지점에서 그린을 공략할 수 있지만 그 이외의 지역은 내리막이 심한 라이가 될 수 있으므로 신중한 전략이 필요합니다", "frontTee": 335, "heightBackTee": -48.4589, "heightChampTee": -48.4589, "heightFrontTee": -37.6598, "heightLadySeniorTee": 0.0, "heightLadyTee": -31.8903, "heightSeniorTee": -35.2679, "holeNo": 5, "ladySeniorTee": 0, "ladyTee": 290, "mapUrl": "/yardage/entire/yardage_entire_157_01_05.jpg", "oCcMasterSeq": null, "oCiNum": null, "screenshot": "screenshot_100000022_1_05.jpg", "seniorTee": 315, "videoMapUrl": "hole3D_157_01_05"}, {"backTee": 530, "basicPar": 5, "ccMasterSeq": 157, "champTee": 500, "ciCode": 100000022, "ciNum": 1, "ciVersion": 2, "courseTypeOrder": 1, "description": "파5홀로 페어웨이가 넓은 좌도그렉 홀 입니다. 페어웨이 좌측으로 공략한다면 투온도 노려볼 수 있으나 그린 앞에 워터해저드가 있으므로 무리한 공략은 피하는 것이 좋습니다. 안전한 쓰리온 작전이 성공한다면 버디도 노려볼 수 있는 홀 입니다", "frontTee": 465, "heightBackTee": -13.1658, "heightChampTee": -10.03, "heightFrontTee": -8.4091, "heightLadySeniorTee": 0.0, "heightLadyTee": -6.0395, "heightSeniorTee": -6.9375, "holeNo": 6, "ladySeniorTee": 0, "ladyTee": 395, "mapUrl": "/yardage/entire/yardage_entire_157_01_06.jpg", "oCcMasterSeq": null, "oCiNum": null, "screenshot": "screenshot_100000022_1_06.jpg", "seniorTee": 430, "videoMapUrl": "hole3D_157_01_06"}, {"backTee": 160, "basicPar": 3, "ccMasterSeq": 157, "champTee": 160, "ciCode": 100000022, "ciNum": 1, "ciVersion": 2, "courseTypeOrder": 1, "description": "파3 아일랜드 홀로 부담이 많이 되는 홀 입니다. 워터해저드의 부담감을 떨쳐버리고 그린공략에만 집중해야 하는 홀 입니다. 워터해저드 위로 멋진 샷을 날려보세요", "frontTee": 121, "heightBackTee": -0.4149, "heightChampTee": -0.4149, "heightFrontTee": 0.3956, "heightLadySeniorTee": 0.0, "heightLadyTee": 0.4703, "heightSeniorTee": 0.4856, "holeNo": 7, "ladySeniorTee": 0, "ladyTee": 117, "mapUrl": "/yardage/entire/yardage_entire_157_01_07.jpg", "oCcMasterSeq": null, "oCiNum": null, "screenshot": "screenshot_100000022_1_07.jpg", "seniorTee": 117, "videoMapUrl": "hole3D_157_01_07"}, {"backTee": 330, "basicPar": 4, "ccMasterSeq": 157, "champTee": 330, "ciCode": 100000022, "ciNum": 1, "ciVersion": 2, "courseTypeOrder": 1, "description": "파4우측 도그렉홀로 페어웨이 중간 우측에 위치해 있는 벙커의 좌측 끝선을 IP로 설정하는 것이 좋습니다. 잘 맞은 볼이 중앙 좌측으로 날아가면 OB의 위험이 있습니다. 티샷만 잘한다면 그린공략은 무난한 홀 입니다. 버디에 도전해 보세요", "frontTee": 310, "heightBackTee": 1.9682, "heightChampTee": 1.9682, "heightFrontTee": 2.366, "heightLadySeniorTee": 0.0, "heightLadyTee": 3.4204, "heightSeniorTee": 3.4546, "holeNo": 8, "ladySeniorTee": 0, "ladyTee": 255, "mapUrl": "/yardage/entire/yardage_entire_157_01_08.jpg", "oCcMasterSeq": null, "oCiNum": null, "screenshot": "screenshot_100000022_1_08.jpg", "seniorTee": 280, "videoMapUrl": "hole3D_157_01_08"}, {"backTee": 380, "basicPar": 4, "ccMasterSeq": 157, "champTee": 380, "ciCode": 100000022, "ciNum": 1, "ciVersion": 2, "courseTypeOrder": 1, "description": "파4홀로 페어웨이 우측 벙커를 피해 티샷 하는 것이 좋습니다. 그린 우측으로 워터해저드가 있으므로 공격적인 공략보다는 그린 중앙으로 편안한 공략을 하는 것이 파세이브를 기록할 수 있는 홀 입니다", "frontTee": 360, "heightBackTee": -3.2712, "heightChampTee": -3.2712, "heightFrontTee": -2.7984, "heightLadySeniorTee": 0.0, "heightLadyTee": 3.1794, "heightSeniorTee": 0.1928, "holeNo": 9, "ladySeniorTee": 0, "ladyTee": 275, "mapUrl": "/yardage/entire/yardage_entire_157_01_09.jpg", "oCcMasterSeq": null, "oCiNum": null, "screenshot": "screenshot_100000022_1_09.jpg", "seniorTee": 315, "videoMapUrl": "hole3D_157_01_09"}], [{"backTee": 480, "basicPar": 5, "ccMasterSeq": 157, "champTee": 465, "ciCode": 100000022, "ciNum": 2, "ciVersion": 2, "courseTypeOrder": 2, "description": "파5홀로 티샷을 할 때 장타자는 좌측 해저드를 유의해야 합니다. 세컨샷 공략에도 좌우에 해저드가 위치하고 있어 신중한 IP설정이 중요합니다. 세컨샷이 페어웨이를 지킨다면 그린공략은 무난한 홀 입니다.", "frontTee": 445, "heightBackTee": -33.9075, "heightChampTee": -33.4773, "heightFrontTee": -28.7249, "heightLadySeniorTee": 0.0, "heightLadyTee": -21.4605, "heightSeniorTee": -23.9457, "holeNo": 1, "ladySeniorTee": 0, "ladyTee": 390, "mapUrl": "/yardage/entire/yardage_entire_157_02_01.jpg", "oCcMasterSeq": null, "oCiNum": null, "screenshot": "screenshot_100000022_2_01(2).jpg", "seniorTee": 405, "videoMapUrl": "hole3D_157_02_01"}, {"backTee": 355, "basicPar": 4, "ccMasterSeq": 157, "champTee": 355, "ciCode": 100000022, "ciNum": 2, "ciVersion": 2, "courseTypeOrder": 2, "description": "파4홀로 티샷은 보기와 다르게 IP지점 페어웨이가 넓으므로 편안한 티샷을 하셔도 됩니다. 하지만 그린이 페어웨이보다 높게 위치하여 그린을 공략할 때는 한클럽정도 길게 보는 것이 좋은 스코어를 기대할 수 있는 홀 입니다", "frontTee": 330, "heightBackTee": 4.5725, "heightChampTee": 4.5725, "heightFrontTee": 6.2012, "heightLadySeniorTee": 0.0, "heightLadyTee": 7.482, "heightSeniorTee": 7.1937, "holeNo": 2, "ladySeniorTee": 0, "ladyTee": 208, "mapUrl": "/yardage/entire/yardage_entire_157_02_02.jpg", "oCcMasterSeq": null, "oCiNum": null, "screenshot": "screenshot_100000022_2_02.jpg", "seniorTee": 285, "videoMapUrl": "hole3D_157_02_02"}, {"backTee": 375, "basicPar": 4, "ccMasterSeq": 157, "champTee": 375, "ciCode": 100000022, "ciNum": 2, "ciVersion": 2, "courseTypeOrder": 2, "description": "내리막이 심한 파4홀로 절벽 밑으로 티샷을 날리는 기분이 듭니다. 슬라이스만 주의한다면 어렵지 않게 페어웨이에 볼을 안착시킬 수 있습니다. 티샷만 페어웨이를 잘 지킨다면 그린공략은 무난한 홀 입니다", "frontTee": 335, "heightBackTee": -50.4037, "heightChampTee": -50.4037, "heightFrontTee": -33.7494, "heightLadySeniorTee": 0.0, "heightLadyTee": -20.7691, "heightSeniorTee": -25.1615, "holeNo": 3, "ladySeniorTee": 0, "ladyTee": 285, "mapUrl": "/yardage/entire/yardage_entire_157_02_03.jpg", "oCcMasterSeq": null, "oCiNum": null, "screenshot": "screenshot_100000022_2_03.jpg", "seniorTee": 300, "videoMapUrl": "hole3D_157_02_03"}, {"backTee": 150, "basicPar": 3, "ccMasterSeq": 157, "champTee": 150, "ciCode": 100000022, "ciNum": 2, "ciVersion": 2, "courseTypeOrder": 2, "description": "좌측으로 해저드가 위치하고 있지만 해저드보다 바다로부터 불어오는 바람의 영향을 유의하여야 하는 홀 입니다. 그린 중앙을 안전하게 공략하는 것이 좋습니다", "frontTee": 135, "heightBackTee": -4.954, "heightChampTee": -4.954, "heightFrontTee": -5.3517, "heightLadySeniorTee": 0.0, "heightLadyTee": -5.3517, "heightSeniorTee": -5.5589, "holeNo": 4, "ladySeniorTee": 0, "ladyTee": 110, "mapUrl": "/yardage/entire/yardage_entire_157_02_04.jpg", "oCcMasterSeq": null, "oCiNum": null, "screenshot": "screenshot_100000022_2_04.jpg", "seniorTee": 125, "videoMapUrl": "hole3D_157_02_04"}, {"backTee": 365, "basicPar": 4, "ccMasterSeq": 157, "champTee": 364, "ciCode": 100000022, "ciNum": 2, "ciVersion": 2, "courseTypeOrder": 2, "description": "좌측으로 해저드가 위치하고 있지만 해저드보다 바다로부터 불어오는 바람의 영향을 유의하여야 하는 홀 입니다. 그린 중앙을 안전하게 공략하는 것이 좋습니다", "frontTee": 335, "heightBackTee": 22.5069, "heightChampTee": 22.5069, "heightFrontTee": 22.0387, "heightLadySeniorTee": 0.0, "heightLadyTee": 15.9074, "heightSeniorTee": 19.2433, "holeNo": 5, "ladySeniorTee": 0, "ladyTee": 265, "mapUrl": "/yardage/entire/yardage_entire_157_02_05.jpg", "oCcMasterSeq": null, "oCiNum": null, "screenshot": "screenshot_100000022_2_05.jpg", "seniorTee": 290, "videoMapUrl": "hole3D_157_02_05"}, {"backTee": 145, "basicPar": 3, "ccMasterSeq": 157, "champTee": 145, "ciCode": 100000022, "ciNum": 2, "ciVersion": 2, "courseTypeOrder": 2, "description": "내리막 파3홀로 내리막을 염두 하여 두클럽 정도 짧게 보는 것이 좋습니다. 티그라운드와 그린사이의 고저차이가 커서 페어웨이가 넓게 보이는 현상이 있지만 그리 넓지 않으므로 무리한 공략보다는 안전한 공략이 필요합니다", "frontTee": 115, "heightBackTee": -21.4835, "heightChampTee": -21.4835, "heightFrontTee": -15.0529, "heightLadySeniorTee": 0.0, "heightLadyTee": -12.3005, "heightSeniorTee": -12.3005, "holeNo": 6, "ladySeniorTee": 0, "ladyTee": 105, "mapUrl": "/yardage/entire/yardage_entire_157_02_06.jpg", "oCcMasterSeq": null, "oCiNum": null, "screenshot": "screenshot_100000022_2_06.jpg", "seniorTee": 105, "videoMapUrl": "hole3D_157_02_06"}, {"backTee": 490, "basicPar": 5, "ccMasterSeq": 157, "champTee": 490, "ciCode": 100000022, "ciNum": 2, "ciVersion": 2, "courseTypeOrder": 2, "description": "내리막이 심한 파5홀로 약간의 훅이나 슬라이스도 위험할 수 있는 홀 입니다. 거리보다는 볼을 안전하게 페어웨이에 안착시키는 것이 중요합니다. 티샷이 페어웨이만 지키면 그린까지의 샷은 그리 어렵지 않습니다. 페어웨이에 언듈레이션이 없어서 어프로치샷의 위험요소는 적은 편이며 그린도 평이한 홀 입니다", "frontTee": 480, "heightBackTee": -32.8718, "heightChampTee": -32.8718, "heightFrontTee": -26.9705, "heightLadySeniorTee": 0.0, "heightLadyTee": 7.1497, "heightSeniorTee": -18.9969, "holeNo": 7, "ladySeniorTee": 0, "ladyTee": 340, "mapUrl": "/yardage/entire/yardage_entire_157_02_07.jpg", "oCcMasterSeq": null, "oCiNum": null, "screenshot": "screenshot_100000022_2_07.jpg", "seniorTee": 465, "videoMapUrl": "hole3D_157_02_07"}, {"backTee": 360, "basicPar": 4, "ccMasterSeq": 157, "champTee": 360, "ciCode": 100000022, "ciNum": 2, "ciVersion": 2, "courseTypeOrder": 2, "description": "파4홀로 티그라운드에서 보면 우측 암벽 때문에 페어웨이가 좁게 느껴지나 IP지점은 넓은 편 입니다. 티샷이 페어웨이를 지킨다면 온그린 공략은 무난하지만 그린의 고저가 높으므로 한클럽정도 길게 공략하는 것이 좋습니다", "frontTee": 310, "heightBackTee": 12.6264, "heightChampTee": 12.6264, "heightFrontTee": 13.793, "heightLadySeniorTee": 0.0, "heightLadyTee": 13.5423, "heightSeniorTee": 14.3977, "holeNo": 8, "ladySeniorTee": 0, "ladyTee": 200, "mapUrl": "/yardage/entire/yardage_entire_157_02_08.jpg", "oCcMasterSeq": null, "oCiNum": null, "screenshot": "screenshot_100000022_2_08.jpg", "seniorTee": 277, "videoMapUrl": "hole3D_157_02_08"}, {"backTee": 335, "basicPar": 4, "ccMasterSeq": 157, "champTee": 335, "ciCode": 100000022, "ciNum": 2, "ciVersion": 2, "courseTypeOrder": 2, "description": "오션코스의 마지막 홀로 파4홀 입니다. 페어웨이 IP지점이 넓어 힘찬 드라이브샷을 할 수 있습니다. 그린공략도 그린 좌우에 위치한 벙커만 유의한다면 좋은 스코어를 기대할 수 있습니다", "frontTee": 315, "heightBackTee": -1.0243, "heightChampTee": -1.0243, "heightFrontTee": -0.6374, "heightLadySeniorTee": 0.0, "heightLadyTee": 0.5776, "heightSeniorTee": -0.4408, "holeNo": 9, "ladySeniorTee": 0, "ladyTee": 255, "mapUrl": "/yardage/entire/yardage_entire_157_02_09.jpg", "oCcMasterSeq": null, "oCiNum": null, "screenshot": "screenshot_100000022_2_09.jpg", "seniorTee": 290, "videoMapUrl": "hole3D_157_02_09"}]], "courseTypes": [{"ciCode": 100000022, "ciNum": 1, "courseName": "VALLEY"}, {"ciCode": 100000022, "ciNum": 2, "courseName": "OCEAN"}]}}