{"ciCode": 100000902, "ccName": "해운대비치골프앤리조트", "detail": {"ciCode": 100000902, "ccName": "해운대비치골프앤리조트", "createdAt": "Y", "country": 1, "district": 5, "address": "부산광역시 기장군 기장읍 대변로 74", "tel": "051-726-0707", "fax": "051-726-0799", "homepageUrl": "https://www.haeundaebeachcc.com/intro/intro.do", "description": "<p style=\"line-height: 18px; font-size: 9pt;\"><strong><span style=\"line-height: 20px; color: rgb(51, 153, 0); font-size: 10pt;\">\"섬세함과 모험이 살아있는 해운대비치골프앤리조트”</span></strong></p><p style=\"line-height: 18px;\"><span style=\"line-height: 20px; font-size: 13.3333px;\">코스와 맞닿은 16개의 넓고 큰 호수 그리고 자연 암반 등의 자연 친화적인 요소들은&nbsp;</span><span style=\"font-size: 13.3333px;\">대자연이 스케치한 그대로의 감동을 느낄 수 있습니다.</span></p>", "difficultyGreen": 7, "difficultyCc": 7, "ciStatus": 1, "ciOption": 14, "areaName": "경상도", "logoImage": "http://uf.spazon.com/course/info/202308/2313/15/6f084c69da8a4188a7ae76aa64f4a2af.jpg", "holeCount": 18, "parCount": 72, "totalWidth": 6413, "boardCount": 6, "ci3d": "Y", "isOnlyHd": null, "isVisionPlus": "Y", "isNgs": "Y", "isOnlyNgs": null, "isTvnx": "Y", "isNxp": "Y", "ciVersion": 2, "tourCc": 0, "ciNight": 1, "membership": "N", "realityYn": "N", "difficultyYn": "N"}, "holeInfo": {"holeInfoList": [[{"backTee": 496, "basicPar": 5, "ccMasterSeq": 989, "champTee": 477, "ciCode": 100000902, "ciNum": 1, "ciVersion": 2, "courseTypeOrder": 1, "description": "", "frontTee": 442, "heightBackTee": -0.605, "heightChampTee": 0.8988, "heightFrontTee": 0.8046, "heightLadySeniorTee": 0.0, "heightLadyTee": 0.6841, "heightSeniorTee": 0.7712, "holeNo": 1, "ladySeniorTee": 0, "ladyTee": 389, "mapUrl": "/yardage/entire/yardage_entire_989_01_01.jpg", "oCcMasterSeq": null, "oCiNum": null, "screenshot": "", "seniorTee": 417, "videoMapUrl": "hole3D_989_01_01"}, {"backTee": 344, "basicPar": 4, "ccMasterSeq": 989, "champTee": 318, "ciCode": 100000902, "ciNum": 1, "ciVersion": 2, "courseTypeOrder": 1, "description": "", "frontTee": 292, "heightBackTee": -12.6928, "heightChampTee": -9.7198, "heightFrontTee": -7.0406, "heightLadySeniorTee": 0.0, "heightLadyTee": -3.9734, "heightSeniorTee": -3.9731, "holeNo": 2, "ladySeniorTee": 0, "ladyTee": 266, "mapUrl": "/yardage/entire/yardage_entire_989_01_02.jpg", "oCcMasterSeq": null, "oCiNum": null, "screenshot": "", "seniorTee": 266, "videoMapUrl": "hole3D_989_01_02"}, {"backTee": 188, "basicPar": 3, "ccMasterSeq": 989, "champTee": 169, "ciCode": 100000902, "ciNum": 1, "ciVersion": 2, "courseTypeOrder": 1, "description": "", "frontTee": 151, "heightBackTee": -2.1158, "heightChampTee": -0.8097, "heightFrontTee": -0.0478, "heightLadySeniorTee": 0.0, "heightLadyTee": 0.8746, "heightSeniorTee": 0.4403, "holeNo": 3, "ladySeniorTee": 0, "ladyTee": 109, "mapUrl": "/yardage/entire/yardage_entire_989_01_03.jpg", "oCcMasterSeq": null, "oCiNum": null, "screenshot": "", "seniorTee": 129, "videoMapUrl": "hole3D_989_01_03"}, {"backTee": 549, "basicPar": 5, "ccMasterSeq": 989, "champTee": 510, "ciCode": 100000902, "ciNum": 1, "ciVersion": 2, "courseTypeOrder": 1, "description": "", "frontTee": 476, "heightBackTee": 13.7598, "heightChampTee": 14.1012, "heightFrontTee": 14.2303, "heightLadySeniorTee": 0.0, "heightLadyTee": 14.2941, "heightSeniorTee": 14.3551, "holeNo": 4, "ladySeniorTee": 0, "ladyTee": 413, "mapUrl": "/yardage/entire/yardage_entire_989_01_04.jpg", "oCcMasterSeq": null, "oCiNum": null, "screenshot": "", "seniorTee": 439, "videoMapUrl": "hole3D_989_01_04"}, {"backTee": 386, "basicPar": 4, "ccMasterSeq": 989, "champTee": 359, "ciCode": 100000902, "ciNum": 1, "ciVersion": 2, "courseTypeOrder": 1, "description": "", "frontTee": 324, "heightBackTee": -15.5788, "heightChampTee": -13.4095, "heightFrontTee": -10.716, "heightLadySeniorTee": 0.0, "heightLadyTee": -5.5899, "heightSeniorTee": -8.0098, "holeNo": 5, "ladySeniorTee": 0, "ladyTee": 254, "mapUrl": "/yardage/entire/yardage_entire_989_01_05.jpg", "oCcMasterSeq": null, "oCiNum": null, "screenshot": "", "seniorTee": 289, "videoMapUrl": "hole3D_989_01_05"}, {"backTee": 381, "basicPar": 4, "ccMasterSeq": 989, "champTee": 361, "ciCode": 100000902, "ciNum": 1, "ciVersion": 2, "courseTypeOrder": 1, "description": "", "frontTee": 339, "heightBackTee": -1.8501, "heightChampTee": -0.7385, "heightFrontTee": 1.0994, "heightLadySeniorTee": 0.0, "heightLadyTee": 4.3539, "heightSeniorTee": 2.6436, "holeNo": 6, "ladySeniorTee": 0, "ladyTee": 293, "mapUrl": "/yardage/entire/yardage_entire_989_01_06.jpg", "oCcMasterSeq": null, "oCiNum": null, "screenshot": "", "seniorTee": 315, "videoMapUrl": "hole3D_989_01_06"}, {"backTee": 148, "basicPar": 3, "ccMasterSeq": 989, "champTee": 128, "ciCode": 100000902, "ciNum": 1, "ciVersion": 2, "courseTypeOrder": 1, "description": "", "frontTee": 115, "heightBackTee": -26.4518, "heightChampTee": -23.2037, "heightFrontTee": -17.2695, "heightLadySeniorTee": 0.0, "heightLadyTee": -9.6519, "heightSeniorTee": -13.2671, "holeNo": 7, "ladySeniorTee": 0, "ladyTee": 70, "mapUrl": "/yardage/entire/yardage_entire_989_01_07.jpg", "oCcMasterSeq": null, "oCiNum": null, "screenshot": "", "seniorTee": 93, "videoMapUrl": "hole3D_989_01_07"}, {"backTee": 322, "basicPar": 4, "ccMasterSeq": 989, "champTee": 314, "ciCode": 100000902, "ciNum": 1, "ciVersion": 2, "courseTypeOrder": 1, "description": "", "frontTee": 296, "heightBackTee": -12.1567, "heightChampTee": -12.1949, "heightFrontTee": -11.8941, "heightLadySeniorTee": 0.0, "heightLadyTee": -8.1446, "heightSeniorTee": -10.3567, "holeNo": 8, "ladySeniorTee": 0, "ladyTee": 218, "mapUrl": "/yardage/entire/yardage_entire_989_01_08.jpg", "oCcMasterSeq": null, "oCiNum": null, "screenshot": "", "seniorTee": 274, "videoMapUrl": "hole3D_989_01_08"}, {"backTee": 337, "basicPar": 4, "ccMasterSeq": 989, "champTee": 320, "ciCode": 100000902, "ciNum": 1, "ciVersion": 2, "courseTypeOrder": 1, "description": "", "frontTee": 298, "heightBackTee": 19.8477, "heightChampTee": 20.468, "heightFrontTee": 20.4681, "heightLadySeniorTee": 0.0, "heightLadyTee": 19.8734, "heightSeniorTee": 19.8734, "holeNo": 9, "ladySeniorTee": 0, "ladyTee": 238, "mapUrl": "/yardage/entire/yardage_entire_989_01_09.jpg", "oCcMasterSeq": null, "oCiNum": null, "screenshot": "", "seniorTee": 254, "videoMapUrl": "hole3D_989_01_09"}], [{"backTee": 367, "basicPar": 4, "ccMasterSeq": 989, "champTee": 342, "ciCode": 100000902, "ciNum": 2, "ciVersion": 2, "courseTypeOrder": 2, "description": "", "frontTee": 308, "heightBackTee": -11.7998, "heightChampTee": -9.755, "heightFrontTee": -7.1685, "heightLadySeniorTee": 0.0, "heightLadyTee": -2.6439, "heightSeniorTee": -5.3177, "holeNo": 1, "ladySeniorTee": 0, "ladyTee": 256, "mapUrl": "/yardage/entire/yardage_entire_989_02_01.jpg", "oCcMasterSeq": null, "oCiNum": null, "screenshot": "", "seniorTee": 282, "videoMapUrl": "hole3D_989_02_01"}, {"backTee": 194, "basicPar": 3, "ccMasterSeq": 989, "champTee": 167, "ciCode": 100000902, "ciNum": 2, "ciVersion": 2, "courseTypeOrder": 2, "description": "", "frontTee": 139, "heightBackTee": -19.4491, "heightChampTee": -13.275, "heightFrontTee": -10.2014, "heightLadySeniorTee": 0.0, "heightLadyTee": -3.2445, "heightSeniorTee": -6.3651, "holeNo": 2, "ladySeniorTee": 0, "ladyTee": 81, "mapUrl": "/yardage/entire/yardage_entire_989_02_02.jpg", "oCcMasterSeq": null, "oCiNum": null, "screenshot": "", "seniorTee": 107, "videoMapUrl": "hole3D_989_02_02"}, {"backTee": 529, "basicPar": 5, "ccMasterSeq": 989, "champTee": 502, "ciCode": 100000902, "ciNum": 2, "ciVersion": 2, "courseTypeOrder": 2, "description": "", "frontTee": 470, "heightBackTee": 3.6087, "heightChampTee": 4.6046, "heightFrontTee": 4.9713, "heightLadySeniorTee": 0.0, "heightLadyTee": 5.8466, "heightSeniorTee": 5.7402, "holeNo": 3, "ladySeniorTee": 0, "ladyTee": 418, "mapUrl": "/yardage/entire/yardage_entire_989_02_03.jpg", "oCcMasterSeq": null, "oCiNum": null, "screenshot": "", "seniorTee": 449, "videoMapUrl": "hole3D_989_02_03"}, {"backTee": 337, "basicPar": 4, "ccMasterSeq": 989, "champTee": 318, "ciCode": 100000902, "ciNum": 2, "ciVersion": 2, "courseTypeOrder": 2, "description": "", "frontTee": 297, "heightBackTee": -9.5254, "heightChampTee": -8.6914, "heightFrontTee": -7.6017, "heightLadySeniorTee": 0.0, "heightLadyTee": -5.2423, "heightSeniorTee": -6.8598, "holeNo": 4, "ladySeniorTee": 0, "ladyTee": 239, "mapUrl": "/yardage/entire/yardage_entire_989_02_04.jpg", "oCcMasterSeq": null, "oCiNum": null, "screenshot": "", "seniorTee": 271, "videoMapUrl": "hole3D_989_02_04"}, {"backTee": 385, "basicPar": 4, "ccMasterSeq": 989, "champTee": 374, "ciCode": 100000902, "ciNum": 2, "ciVersion": 2, "courseTypeOrder": 2, "description": "", "frontTee": 348, "heightBackTee": 3.3964, "heightChampTee": 3.5609, "heightFrontTee": 3.6743, "heightLadySeniorTee": 0.0, "heightLadyTee": 4.3691, "heightSeniorTee": 3.8216, "holeNo": 5, "ladySeniorTee": 0, "ladyTee": 304, "mapUrl": "/yardage/entire/yardage_entire_989_02_05.jpg", "oCcMasterSeq": null, "oCiNum": null, "screenshot": "", "seniorTee": 326, "videoMapUrl": "hole3D_989_02_05"}, {"backTee": 197, "basicPar": 3, "ccMasterSeq": 989, "champTee": 177, "ciCode": 100000902, "ciNum": 2, "ciVersion": 2, "courseTypeOrder": 2, "description": "", "frontTee": 140, "heightBackTee": -1.8144, "heightChampTee": -0.8226, "heightFrontTee": -0.1488, "heightLadySeniorTee": 0.0, "heightLadyTee": 1.0275, "heightSeniorTee": 0.7004, "holeNo": 6, "ladySeniorTee": 0, "ladyTee": 96, "mapUrl": "/yardage/entire/yardage_entire_989_02_06.jpg", "oCcMasterSeq": null, "oCiNum": null, "screenshot": "", "seniorTee": 118, "videoMapUrl": "hole3D_989_02_06"}, {"backTee": 544, "basicPar": 5, "ccMasterSeq": 989, "champTee": 525, "ciCode": 100000902, "ciNum": 2, "ciVersion": 2, "courseTypeOrder": 2, "description": "", "frontTee": 491, "heightBackTee": 18.2008, "heightChampTee": 18.0132, "heightFrontTee": 17.4323, "heightLadySeniorTee": 0.0, "heightLadyTee": 16.85, "heightSeniorTee": 16.85, "holeNo": 7, "ladySeniorTee": 0, "ladyTee": 445, "mapUrl": "/yardage/entire/yardage_entire_989_02_07.jpg", "oCcMasterSeq": null, "oCiNum": null, "screenshot": "", "seniorTee": 446, "videoMapUrl": "hole3D_989_02_07"}, {"backTee": 375, "basicPar": 4, "ccMasterSeq": 989, "champTee": 353, "ciCode": 100000902, "ciNum": 2, "ciVersion": 2, "courseTypeOrder": 2, "description": "", "frontTee": 323, "heightBackTee": -22.2625, "heightChampTee": -20.1964, "heightFrontTee": -17.0487, "heightLadySeniorTee": 0.0, "heightLadyTee": -13.7343, "heightSeniorTee": -13.7343, "holeNo": 8, "ladySeniorTee": 0, "ladyTee": 279, "mapUrl": "/yardage/entire/yardage_entire_989_02_08.jpg", "oCcMasterSeq": null, "oCiNum": null, "screenshot": "", "seniorTee": 280, "videoMapUrl": "hole3D_989_02_08"}, {"backTee": 334, "basicPar": 4, "ccMasterSeq": 989, "champTee": 314, "ciCode": 100000902, "ciNum": 2, "ciVersion": 2, "courseTypeOrder": 2, "description": "", "frontTee": 291, "heightBackTee": 13.1921, "heightChampTee": 13.5683, "heightFrontTee": 13.4211, "heightLadySeniorTee": 0.0, "heightLadyTee": 13.4612, "heightSeniorTee": 13.2203, "holeNo": 9, "ladySeniorTee": 0, "ladyTee": 239, "mapUrl": "/yardage/entire/yardage_entire_989_02_09.jpg", "oCcMasterSeq": null, "oCiNum": null, "screenshot": "", "seniorTee": 267, "videoMapUrl": "hole3D_989_02_09"}]], "courseTypes": [{"ciCode": 100000902, "ciNum": 1, "courseName": "마운틴"}, {"ciCode": 100000902, "ciNum": 2, "courseName": "오션"}]}}