{
 "course": "크리스밸리 CC",
 "source": "골프존 코스 데이터 (파·거리·고도차) · 홀 영상 제공: 골프존",
 "sourceUrl": "https://www.creasvalley.com/ ",
 "courses": [
  {
   "name": "OUT",
   "holes": [
    {
     "no": 1,
     "par": 4,
     "tees": [
      {
       "name": "챔피언",
       "m": 367
      },
      {
       "name": "백",
       "m": 388
      },
      {
       "name": "프론트",
       "m": 353
      },
      {
       "name": "시니어",
       "m": 330
      },
      {
       "name": "레이디",
       "m": 294
      }
     ],
     "len": 367,
     "elev": 16,
     "video": "https://mediathumbnail.golfzon.com/media/cc/hole3d/hole3D_1325_01_01.mp4"
    },
    {
     "no": 2,
     "par": 5,
     "tees": [
      {
       "name": "챔피언",
       "m": 446
      },
      {
       "name": "백",
       "m": 473
      },
      {
       "name": "프론트",
       "m": 424
      },
      {
       "name": "시니어",
       "m": 396
      },
      {
       "name": "레이디",
       "m": 372
      }
     ],
     "len": 446,
     "elev": -19,
     "video": "https://mediathumbnail.golfzon.com/media/cc/hole3d/hole3D_1325_01_02.mp4"
    },
    {
     "no": 3,
     "par": 4,
     "tees": [
      {
       "name": "챔피언",
       "m": 323
      },
      {
       "name": "백",
       "m": 352
      },
      {
       "name": "프론트",
       "m": 292
      },
      {
       "name": "시니어",
       "m": 270
      },
      {
       "name": "레이디",
       "m": 252
      }
     ],
     "len": 323,
     "elev": -7,
     "video": "https://mediathumbnail.golfzon.com/media/cc/hole3d/hole3D_1325_01_03.mp4"
    },
    {
     "no": 4,
     "par": 4,
     "tees": [
      {
       "name": "챔피언",
       "m": 295
      },
      {
       "name": "백",
       "m": 316
      },
      {
       "name": "프론트",
       "m": 276
      },
      {
       "name": "시니어",
       "m": 258
      },
      {
       "name": "레이디",
       "m": 241
      }
     ],
     "len": 295,
     "elev": -50,
     "video": "https://mediathumbnail.golfzon.com/media/cc/hole3d/hole3D_1325_01_04.mp4"
    },
    {
     "no": 5,
     "par": 3,
     "tees": [
      {
       "name": "챔피언",
       "m": 133
      },
      {
       "name": "백",
       "m": 152
      },
      {
       "name": "프론트",
       "m": 119
      },
      {
       "name": "시니어",
       "m": 105
      },
      {
       "name": "레이디",
       "m": 88
      }
     ],
     "len": 133,
     "elev": -24,
     "video": "https://mediathumbnail.golfzon.com/media/cc/hole3d/hole3D_1325_01_05.mp4"
    },
    {
     "no": 6,
     "par": 5,
     "tees": [
      {
       "name": "챔피언",
       "m": 481
      },
      {
       "name": "백",
       "m": 501
      },
      {
       "name": "프론트",
       "m": 458
      },
      {
       "name": "시니어",
       "m": 387
      },
      {
       "name": "레이디",
       "m": 348
      }
     ],
     "len": 481,
     "elev": 16,
     "video": "https://mediathumbnail.golfzon.com/media/cc/hole3d/hole3D_1325_01_06.mp4"
    },
    {
     "no": 7,
     "par": 4,
     "tees": [
      {
       "name": "챔피언",
       "m": 305
      },
      {
       "name": "백",
       "m": 330
      },
      {
       "name": "프론트",
       "m": 291
      },
      {
       "name": "시니어",
       "m": 226
      },
      {
       "name": "레이디",
       "m": 215
      }
     ],
     "len": 305,
     "elev": 15,
     "video": "https://mediathumbnail.golfzon.com/media/cc/hole3d/hole3D_1325_01_07.mp4"
    },
    {
     "no": 8,
     "par": 3,
     "tees": [
      {
       "name": "챔피언",
       "m": 128
      },
      {
       "name": "백",
       "m": 156
      },
      {
       "name": "프론트",
       "m": 124
      },
      {
       "name": "시니어",
       "m": 101
      },
      {
       "name": "레이디",
       "m": 93
      }
     ],
     "len": 128,
     "video": "https://mediathumbnail.golfzon.com/media/cc/hole3d/hole3D_1325_01_08.mp4"
    },
    {
     "no": 9,
     "par": 4,
     "tees": [
      {
       "name": "챔피언",
       "m": 404
      },
      {
       "name": "백",
       "m": 428
      },
      {
       "name": "프론트",
       "m": 388
      },
      {
       "name": "시니어",
       "m": 352
      },
      {
       "name": "레이디",
       "m": 311
      }
     ],
     "len": 404,
     "elev": -20,
     "video": "https://mediathumbnail.golfzon.com/media/cc/hole3d/hole3D_1325_01_09.mp4"
    }
   ]
  },
  {
   "name": "IN",
   "holes": [
    {
     "no": 1,
     "par": 4,
     "tees": [
      {
       "name": "챔피언",
       "m": 345
      },
      {
       "name": "백",
       "m": 370
      },
      {
       "name": "프론트",
       "m": 327
      },
      {
       "name": "시니어",
       "m": 305
      },
      {
       "name": "레이디",
       "m": 282
      }
     ],
     "len": 345,
     "elev": -20,
     "video": "https://mediathumbnail.golfzon.com/media/cc/hole3d/hole3D_1325_02_01.mp4"
    },
    {
     "no": 2,
     "par": 4,
     "tees": [
      {
       "name": "챔피언",
       "m": 324
      },
      {
       "name": "백",
       "m": 348
      },
      {
       "name": "프론트",
       "m": 313
      },
      {
       "name": "시니어",
       "m": 288
      },
      {
       "name": "레이디",
       "m": 258
      }
     ],
     "len": 324,
     "elev": 18,
     "video": "https://mediathumbnail.golfzon.com/media/cc/hole3d/hole3D_1325_02_02.mp4"
    },
    {
     "no": 3,
     "par": 3,
     "tees": [
      {
       "name": "챔피언",
       "m": 151
      },
      {
       "name": "백",
       "m": 179
      },
      {
       "name": "프론트",
       "m": 123
      },
      {
       "name": "시니어",
       "m": 109
      },
      {
       "name": "레이디",
       "m": 108
      }
     ],
     "len": 151,
     "elev": -23,
     "video": "https://mediathumbnail.golfzon.com/media/cc/hole3d/hole3D_1325_02_03.mp4"
    },
    {
     "no": 4,
     "par": 5,
     "tees": [
      {
       "name": "챔피언",
       "m": 446
      },
      {
       "name": "백",
       "m": 475
      },
      {
       "name": "프론트",
       "m": 434
      },
      {
       "name": "시니어",
       "m": 407
      },
      {
       "name": "레이디",
       "m": 355
      }
     ],
     "len": 446,
     "elev": 44,
     "video": "https://mediathumbnail.golfzon.com/media/cc/hole3d/hole3D_1325_02_04.mp4"
    },
    {
     "no": 5,
     "par": 4,
     "tees": [
      {
       "name": "챔피언",
       "m": 273
      },
      {
       "name": "백",
       "m": 299
      },
      {
       "name": "프론트",
       "m": 257
      },
      {
       "name": "시니어",
       "m": 231
      },
      {
       "name": "레이디",
       "m": 206
      }
     ],
     "len": 273,
     "elev": -5,
     "video": "https://mediathumbnail.golfzon.com/media/cc/hole3d/hole3D_1325_02_05.mp4"
    },
    {
     "no": 6,
     "par": 4,
     "tees": [
      {
       "name": "챔피언",
       "m": 359
      },
      {
       "name": "백",
       "m": 386
      },
      {
       "name": "프론트",
       "m": 342
      },
      {
       "name": "시니어",
       "m": 317
      },
      {
       "name": "레이디",
       "m": 279
      }
     ],
     "len": 359,
     "elev": 11,
     "video": "https://mediathumbnail.golfzon.com/media/cc/hole3d/hole3D_1325_02_06.mp4"
    },
    {
     "no": 7,
     "par": 5,
     "tees": [
      {
       "name": "챔피언",
       "m": 480
      },
      {
       "name": "백",
       "m": 499
      },
      {
       "name": "프론트",
       "m": 457
      },
      {
       "name": "시니어",
       "m": 438
      },
      {
       "name": "레이디",
       "m": 420
      }
     ],
     "len": 480,
     "elev": -55,
     "video": "https://mediathumbnail.golfzon.com/media/cc/hole3d/hole3D_1325_02_07.mp4"
    },
    {
     "no": 8,
     "par": 3,
     "tees": [
      {
       "name": "챔피언",
       "m": 162
      },
      {
       "name": "백",
       "m": 181
      },
      {
       "name": "프론트",
       "m": 146
      },
      {
       "name": "시니어",
       "m": 128
      },
      {
       "name": "레이디",
       "m": 109
      }
     ],
     "len": 162,
     "elev": -21,
     "video": "https://mediathumbnail.golfzon.com/media/cc/hole3d/hole3D_1325_02_08.mp4"
    },
    {
     "no": 9,
     "par": 4,
     "tees": [
      {
       "name": "챔피언",
       "m": 348
      },
      {
       "name": "백",
       "m": 372
      },
      {
       "name": "프론트",
       "m": 317
      },
      {
       "name": "시니어",
       "m": 309
      },
      {
       "name": "레이디",
       "m": 252
      }
     ],
     "len": 348,
     "video": "https://mediathumbnail.golfzon.com/media/cc/hole3d/hole3D_1325_02_09.mp4"
    }
   ]
  }
 ]
}