{
 "seed": "http://www.goldenbay.kr",
 "pages": {
  "p0.html": "http://www.goldenbay.kr",
  "p1.html": "https://www.goldenbay.kr/about/guide.asp",
  "p2.html": "https://www.goldenbay.kr/about/guide.asp?tab=3",
  "p3.html": "https://www.goldenbay.kr/course/course-info.asp",
  "p4.html": "https://www.goldenbay.kr/course/mountain.asp",
  "p5.html": "https://www.goldenbay.kr/course/ocean.asp",
  "p6.html": "https://www.goldenbay.kr/course/valley.asp"
 },
 "images": {
  "course_planner.jpg": "https://www.goldenbay.kr/images/course/course_planner.jpg",
  "mountain.jpg": "https://www.goldenbay.kr/images/course/mountain.jpg",
  "ocean.jpg": "https://www.goldenbay.kr/images/course/ocean.jpg",
  "valley.jpg": "https://www.goldenbay.kr/images/course/valley.jpg",
  "m1.png": "https://www.goldenbay.kr/images/course/mountain/m1.png",
  "m2.png": "https://www.goldenbay.kr/images/course/mountain/m2.png",
  "m3.png": "https://www.goldenbay.kr/images/course/mountain/m3.png",
  "m4.png": "https://www.goldenbay.kr/images/course/mountain/m4.png",
  "m5.png": "https://www.goldenbay.kr/images/course/mountain/m5.png",
  "m6.png": "https://www.goldenbay.kr/images/course/mountain/m6.png",
  "m7.png": "https://www.goldenbay.kr/images/course/mountain/m7.png",
  "m8.png": "https://www.goldenbay.kr/images/course/mountain/m8.png",
  "m9.png": "https://www.goldenbay.kr/images/course/mountain/m9.png",
  "o1.png": "https://www.goldenbay.kr/images/course/ocean/o1.png",
  "o2.png": "https://www.goldenbay.kr/images/course/ocean/o2.png",
  "o3.png": "https://www.goldenbay.kr/images/course/ocean/o3.png",
  "o4.png": "https://www.goldenbay.kr/images/course/ocean/o4.png",
  "o5.png": "https://www.goldenbay.kr/images/course/ocean/o5.png",
  "o6.png": "https://www.goldenbay.kr/images/course/ocean/o6.png",
  "o7.png": "https://www.goldenbay.kr/images/course/ocean/o7.png",
  "o8.png": "https://www.goldenbay.kr/images/course/ocean/o8.png",
  "o9.png": "https://www.goldenbay.kr/images/course/ocean/o9.png",
  "v1.png": "https://www.goldenbay.kr/images/course/valley/v1.png",
  "v2.png": "https://www.goldenbay.kr/images/course/valley/v2.png",
  "v3.png": "https://www.goldenbay.kr/images/course/valley/v3.png",
  "v4.png": "https://www.goldenbay.kr/images/course/valley/v4.png",
  "v5.png": "https://www.goldenbay.kr/images/course/valley/v5.png",
  "v6.png": "https://www.goldenbay.kr/images/course/valley/v6.png",
  "v7.png": "https://www.goldenbay.kr/images/course/valley/v7.png",
  "v8.png": "https://www.goldenbay.kr/images/course/valley/v8.png",
  "v9.png": "https://www.goldenbay.kr/images/course/valley/v9.png"
 },
 "errors": []
}