{
 "name": "알펜시아 트룬CC",
 "seed": "https://www.alpensia.com/golf/main.do",
 "pages": {
  "p0.html": "https://www.alpensia.com/golf/main.do",
  "p1.html": "https://www.alpensia.com/golf/trooncc/course-info.do",
  "p2.html": "https://www.alpensia.com/golf/trooncc/course-forest-hole1.do",
  "p3.html": "https://www.alpensia.com/golf/trooncc/course-lake-hole1.do",
  "p4.html": "https://www.alpensia.com/golf/trooncc/course-meadow-hole1.do",
  "p5.html": "https://www.alpensia.com/golf/gc700/course-info.do",
  "p6.html": "https://www.alpensia.com/golf/gc700/course-alps-hole1.do",
  "p7.html": "https://www.alpensia.com/golf/gc700/course-asia-hole10.do",
  "p8.html": "https://www.alpensia.com/ski/use-cost-training.do",
  "p9.html": "https://www.alpensia.com/ski/use-cost-lift.do",
  "p10.html": "https://www.alpensia.com/ski/use-cost-rental.do",
  "p11.html": "https://www.alpensia.com/ski/use-cost-sled.do",
  "p12.html": "https://www.alpensia.com/ocean/use-cost.do",
  "p13.html": "https://www.alpensia.com/lc/cost-info.do"
 },
 "images": {
  "lc_cost_info.jpg": "https://www.alpensia.com/images/lc/lc_cost_info.jpg",
  "course_lake_hole1.jpg": "https://www.alpensia.com/images/golf/trooncc/course_lake_hole1.jpg",
  "sky_lift_cost.jpg": "https://www.alpensia.com/images/ski/sky_lift_cost.jpg",
  "ski_sled_cost.jpg": "https://www.alpensia.com/images/ski/ski_sled_cost.jpg",
  "course_forest_hole1.jpg": "https://www.alpensia.com/images/golf/trooncc/course_forest_hole1.jpg",
  "kv_course_gc700.jpg": "https://www.alpensia.com/images/kv/kv_course_gc700.jpg",
  "ski_rental_cost.jpg": "https://www.alpensia.com/images/ski/ski_rental_cost.jpg",
  "course_alps_hole01.jpg": "https://www.alpensia.com/images/golf/gc700/course_alps_hole01.jpg",
  "kv_course_forest.jpg": "https://www.alpensia.com/images/kv/kv_course_forest.jpg",
  "course_meadow_hole1.jpg": "https://www.alpensia.com/images/golf/trooncc/course_meadow_hole1.jpg",
  "course_asia_hole10.jpg": "https://www.alpensia.com/images/golf/gc700/course_asia_hole10.jpg",
  "ski_intro.jpg": "https://www.alpensia.com/images/kv/ski_intro.jpg",
  "ocean_use-guide.gif": "https://www.alpensia.com/images/ocean700/ocean_use-guide.gif",
  "lc_intro.jpg": "https://www.alpensia.com/images/kv/lc_intro.jpg",
  "ocean_intro.jpg": "https://www.alpensia.com/images/kv/ocean_intro.jpg"
 },
 "errors": []
}