{
 "seed": "https://illitegolfnresort.co.kr/",
 "pages": {
  "p0.html": "https://illitegolfnresort.co.kr/",
  "p1.html": "https://illitegolfnresort.co.kr/course",
  "p2.html": "https://illitegolfnresort.co.kr/course/course.asp",
  "p3.html": "https://illitegolfnresort.co.kr/golf/course",
  "p4.html": "https://illitegolfnresort.co.kr/sub/course",
  "p5.html": "https://illitegolfnresort.co.kr/course_info",
  "p6.html": "https://illitegolfnresort.co.kr/club/course",
  "p7.html": "https://illitegolfnresort.co.kr/kor/course",
  "p8.html": "https://illitegolfnresort.co.kr/course01"
 },
 "images": {},
 "errors": []
}