{
 "seed": "https://www.ghcc.kr/main.asp",
 "pages": {
  "p0.html": "https://www.ghcc.kr/main.asp",
  "p1.html": "https://www.ghcc.kr/main.asp/course",
  "p2.html": "https://www.ghcc.kr/main.asp/course/course.asp",
  "p3.html": "https://www.ghcc.kr/main.asp/golf/course",
  "p4.html": "https://www.ghcc.kr/main.asp/sub/course",
  "p5.html": "https://www.ghcc.kr/main.asp/course_info",
  "p6.html": "https://www.ghcc.kr/main.asp/club/course",
  "p7.html": "https://www.ghcc.kr/main.asp/kor/course",
  "p8.html": "https://www.ghcc.kr/main.asp/course01"
 },
 "images": {},
 "errors": []
}